inferscope/__init__.py
inferscope/__version__.py
inferscope/_utils.py
inferscope/artifacts.py
inferscope/client.py
inferscope/run.py
inferscope/models/__init__.py
inferscope/models/artifact.py
inferscope/models/data_description.py
inferscope/models/dataset.py
inferscope/models/experiment.py
inferscope/models/find_filter.py
inferscope/models/interactive_base.py
inferscope/models/metric.py
inferscope/models/model.py
inferscope/models/project.py
inferscope/models/run.py
inferscope/models/user.py
inferscope-0.1.1.dist-info/LICENSE
inferscope-0.1.1.dist-info/METADATA
inferscope-0.1.1.dist-info/WHEEL
inferscope-0.1.1.dist-info/top_level.txt
inferscope-0.1.1.dist-info/RECORD
