Metadata-Version: 2.1
Name: inferscope
Version: 0.1.1
Summary: Python-package for inferscope mlops service
Author: kizill
Author-email: staskirillov@gmail.com
Keywords: ml,mlops
Requires-Python: >=3.9.0
License-File: LICENSE
Requires-Dist: attr
Requires-Dist: attrs
Requires-Dist: httpx[http2]
Requires-Dist: pydantic>2.0
